pyboiler/__init__.py
pyboiler/changelog.py
pyboiler/cli.py
pyboiler/color.py
pyboiler/config.py
pyboiler/error.py
pyboiler/generic.py
pyboiler/hml.py
pyboiler/hson.py
pyboiler/imports.py
pyboiler/logger.py
pyboiler/logging.py
pyboiler/platform.py
pyboiler/profiler.py
pyboiler/settings.py
pyboiler/version.py
pyboiler/internal/__init__.py
pyboiler/internal/cli/progress.py
pyboiler/internal/color/__init__.py
pyboiler/internal/color/colors.py
pyboiler/internal/color/config.py
pyboiler/internal/color/parse.py
pyboiler/internal/log/__init__.py
pyboiler/internal/log/config.py
pyboiler/internal/log/filter.py
pyboiler/internal/log/format.py
pyboiler/internal/log/handler.py
pyboiler/internal/log/inspect.py
pyboiler/internal/log/level.py
pyboiler/internal/log/queue.py
pyboiler/internal/log/record.py
pyboiler_anonoei-0.4.0.dist-info/LICENSE
pyboiler_anonoei-0.4.0.dist-info/METADATA
pyboiler_anonoei-0.4.0.dist-info/WHEEL
pyboiler_anonoei-0.4.0.dist-info/top_level.txt
pyboiler_anonoei-0.4.0.dist-info/RECORD
