Metadata-Version: 2.1
Name: pyboiler_anonoei
Version: 0.4.0
Summary: Various generic python helpers so I don't keep rewriting them
Author-email: Anonoei <dev@anonoei.com>
Project-URL: Homepage, https://github.com/anonoei/pyboiler
Project-URL: Documentation, https://anonoei.github.io/pyboiler/
Project-URL: Repository, https://github.com/Anonoei/pyboiler.git
Project-URL: Issues, https://github.com/Anonoei/pyboiler/issues
Project-URL: Source, https://github.com/anonoei/pyboiler
Keywords: anonoei,boilerplate
Classifier: Development Status :: 4 - Beta
Classifier: Intended Audience :: Developers
Classifier: License :: OSI Approved :: MIT License
Classifier: Programming Language :: Python :: 3
Classifier: Operating System :: OS Independent
Requires-Python: >=3.6
License-File: LICENSE
Provides-Extra: dev
Requires-Dist: twine ; extra == 'dev'
Requires-Dist: build ; extra == 'dev'
Requires-Dist: black ; extra == 'dev'
Requires-Dist: bumpver ; extra == 'dev'
Requires-Dist: pytest ; extra == 'dev'
Requires-Dist: pdoc3 ; extra == 'dev'
